Workbook

Sheet Dashboard
B2: Sales Performance Analysis Dashboard
B5: TOTAL REVENUE | D5: TOTAL PROFIT | F5: TOTAL ORDERS | H5: AVG. ORDER VALUE
B6: =SUM(Summary!B7:B12) -> 644384 | D6: =SUM(Summary!C7:C12) -> 243847 | F6: =COUNTA('Raw Data'!$A$2:$A$222) -> 221 | H6: =D6/F6 -> 1103.3801

Sheet Raw Data
A1: OrderID | B1: Date | C1: Month | D1: Region | E1: Category | F1: Product | G1: CustomerID | H1: Quantity | I1: Unit Price (₹) | J1: Unit Cost (₹) | K1: Revenue (₹) | L1: Cost (₹) | M1: Profit (₹)
A2: ORD-1001 | B2: 46027 | C2: =TEXT(B2,"mmm") -> Jan | D2: Kolkata (East Zone) | E2: Stationery | F2: Notebook Set | G2: CUST-039 | H2: 1 | I2: 1299 | J2: 963 | K2: =H2*I2 -> 1299 | L2: =H2*J2 -> 963 | M2: =K2-L2 -> 336
A3: ORD-1002 | B3: 46027 | C3: =TEXT(B3,"mmm") -> Jan | D3: Delhi (North Zone) | E3: Apparel | F3: Rain Jacket | G3: CUST-030 | H3: 2 | I3: 1999 | J3: 1211 | K3: =H3*I3 -> 3998 | L3: =H3*J3 -> 2422 | M3: =K3-L3 -> 1576
A4: ORD-1003 | B4: 46028 | C4: =TEXT(B4,"mmm") -> Jan | D4: Kolkata (East Zone) | E4: Electronics | F4: Smart Watch | G4: CUST-041 | H4: 2 | I4: 1499 | J4: 898 | K4: =H4*I4 -> 2998 | L4: =H4*J4 -> 1796 | M4: =K4-L4 -> 1202
A5: ORD-1004 | B5: 46028 | C5: =TEXT(B5,"mmm") -> Jan | D5: Kolkata (East Zone) | E5: Stationery | F5: Desk Organizer | G5: CUST-037 | H5: 1 | I5: 1999 | J5: 1140 | K5: =H5*I5 -> 1999 | L5: =H5*J5 -> 1140 | M5: =K5-L5 -> 859
A6: ORD-1005 | B6: 46029 | C6: =TEXT(B6,"mmm") -> Jan | D6: Bengaluru (South Zone) | E6: Apparel | F6: Running Shoes | G6: CUST-019 | H6: 1 | I6: 499 | J6: 350 | K6: =H6*I6 -> 499 | L6: =H6*J6 -> 350 | M6: =K6-L6 -> 149
A7: ORD-1006 | B7: 46030 | C7: =TEXT(B7,"mmm") -> Jan | D7: Kolkata (East Zone) | E7: Home Appliances | F7: Air Fryer | G7: CUST-030 | H7: 3 | I7: 3499 | J7: 2346 | K7: =H7*I7 -> 10497 | L7: =H7*J7 -> 7038 | M7: =K7-L7 -> 3459
A8: ORD-1007 | B8: 46031 | C8: =TEXT(B8,"mmm") -> Jan | D8: Kolkata (East Zone) | E8: Home Appliances | F8: Electric Kettle | G8: CUST-014 | H8: 3 | I8: 799 | J8: 474 | K8: =H8*I8 -> 2397 | L8: =H8*J8 -> 1422 | M8: =K8-L8 -> 975
A9: ORD-1008 | B9: 46032 | C9: =TEXT(B9,"mmm") -> Jan | D9: Bengaluru (South Zone) | E9: Furniture | F9: Bookshelf | G9: CUST-035 | H9: 3 | I9: 2999 | J9: 2003 | K9: =H9*I9 -> 8997 | L9: =H9*J9 -> 6009 | M9: =K9-L9 -> 2988
A10: ORD-1009 | B10: 46034 | C10: =TEXT(B10,"mmm") -> Jan | D10: Kolkata (East Zone) | E10: Home Appliances | F10: Air Fryer | G10: CUST-041 | H10: 3 | I10: 3499 | J10: 2346 | K10: =H10*I10 -> 10497 | L10: =H10*J10 -> 7038 | M10: =K10-L10 -> 3459
A11: ORD-1010 | B11: 46034 | C11: =TEXT(B11,"mmm") -> Jan | D11: Bengaluru (South Zone) | E11: Furniture | F11: Study Table | G11: CUST-044 | H11: 1 | I11: 3499 | J11: 2218 | K11: =H11*I11 -> 3499 | L11: =H11*J11 -> 2218 | M11: =K11-L11 -> 1281
A12: ORD-1011 | B12: 46035 | C12: =TEXT(B12,"mmm") -> Jan | D12: Delhi (North Zone) | E12: Electronics | F12: Power Bank | G12: CUST-021 | H12: 2 | I12: 3499 | J12: 1985 | K12: =H12*I12 -> 6998 | L12: =H12*J12 -> 3970 | M12: =K12-L12 -> 3028
A13: ORD-1012 | B13: 46036 | C13: =TEXT(B13,"mmm") -> Jan | D13: Kolkata (East Zone) | E13: Stationery | F13: Desk Organizer | G13: CUST-014 | H13: 3 | I13: 1999 | J13: 1140 | K13: =H13*I13 -> 5997 | L13: =H13*J13 -> 3420 | M13: =K13-L13 -> 2577
... A222: ORD-1221 | B222: 46185 | C222: =TEXT(B222,"mmm") -> Jun | D222: Mumbai (West Zone) | E222: Stationery | F222: Desk Organizer | G222: CUST-019 | H222: 1 | I222: 1999 | J222: 1140 | K222: =H222*I222 -> 1999 | L222: =H222*J222 -> 1140 | M222: =K222-L222 -> 859

Sheet Summary
A1: Sales Performance Analysis — Summary Tables
A4: Month-wise Revenue & Profit
A5: Month | B5: Revenue (₹) | C5: Profit (₹) | D5: Orders
A6: Jan | B6: =SUMIFS('Raw Data'!$K$2:$K$222,'Raw Data'!$C$2:$C$222,A6) -> 118544 | C6: =SUMIFS('Raw Data'!$M$2:$M$222,'Raw Data'!$C$2:$C$222,A6) -> 43884 | D6: =COUNTIFS('Raw Data'!$C$2:$C$222,A6) -> 34
A7: Feb | B7: =SUMIFS('Raw Data'!$K$2:$K$222,'Raw Data'!$C$2:$C$222,A7) -> 98051 | C7: =SUMIFS('Raw Data'!$M$2:$M$222,'Raw Data'!$C$2:$C$222,A7) -> 37013 | D7: =COUNTIFS('Raw Data'!$C$2:$C$222,A7) -> 33
A8: Mar | B8: =SUMIFS('Raw Data'!$K$2:$K$222,'Raw Data'!$C$2:$C$222,A8) -> 151926 | C8: =SUMIFS('Raw Data'!$M$2:$M$222,'Raw Data'!$C$2:$C$222,A8) -> 58191 | D8: =COUNTIFS('Raw Data'!$C$2:$C$222,A8) -> 41
A9: Apr | B9: =SUMIFS('Raw Data'!$K$2:$K$222,'Raw Data'!$C$2:$C$222,A9) -> 166621 | C9: =SUMIFS('Raw Data'!$M$2:$M$222,'Raw Data'!$C$2:$C$222,A9) -> 62918 | D9: =COUNTIFS('Raw Data'!$C$2:$C$222,A9) -> 47
A10: May | B10: =SUMIFS('Raw Data'!$K$2:$K$222,'Raw Data'!$C$2:$C$222,A10) -> 183214 | C10: =SUMIFS('Raw Data'!$M$2:$M$222,'Raw Data'!$C$2:$C$222,A10) -> 69632 | D10: =COUNTIFS('Raw Data'!$C$2:$C$222,A10) -> 49
A11: Jun | B11: =SUMIFS('Raw Data'!$K$2:$K$222,'Raw Data'!$C$2:$C$222,A11) -> 44572 | C11: =SUMIFS('Raw Data'!$M$2:$M$222,'Raw Data'!$C$2:$C$222,A11) -> 16093 | D11: =COUNTIFS('Raw Data'!$C$2:$C$222,A11) -> 17
A14: Region-wise Revenue & Profit
A15: Region | B15: Revenue (₹) | C15: Profit (₹) | D15: Orders
A16: Delhi (North Zone) | B16: =SUMIFS('Raw Data'!$K$2:$K$222,'Raw Data'!$D$2:$D$222,A16) -> 219504 | C16: =SUMIFS('Raw Data'!$M$2:$M$222,'Raw Data'!$D$2:$D$222,A16) -> 83184 | D16: =COUNTIFS('Raw Data'!$D$2:$D$222,A16) -> 60
A17: Bengaluru (South Zone) | B17: =SUMIFS('Raw Data'!$K$2:$K$222,'Raw Data'!$D$2:$D$222,A17) -> 155321 | C17: =SUMIFS('Raw Data'!$M$2:$M$222,'Raw Data'!$D$2:$D$222,A17) -> 57723 | D17: =COUNTIFS('Raw Data'!$D$2:$D$222,A17) -> 46
A18: Kolkata (East Zone) | B18: =SUMIFS('Raw Data'!$K$2:$K$222,'Raw Data'!$D$2:$D$222,A18) -> 203899 | C18: =SUMIFS('Raw Data'!$M$2:$M$222,'Raw Data'!$D$2:$D$222,A18) -> 75808 | D18: =COUNTIFS('Raw Data'!$D$2:$D$222,A18) -> 60
A19: Mumbai (West Zone) | B19: =SUMIFS('Raw Data'!$K$2:$K$222,'Raw Data'!$D$2:$D$222,A19) -> 184204 | C19: =SUMIFS('Raw Data'!$M$2:$M$222,'Raw Data'!$D$2:$D$222,A19) -> 71016 | D19: =COUNTIFS('Raw Data'!$D$2:$D$222,A19) -> 55
A22: Category-wise Revenue & Profit
A23: Category | B23: Revenue (₹) | C23: Profit (₹)
A24: Electronics | B24: =SUMIFS('Raw Data'!$K$2:$K$222,'Raw Data'!$E$2:$E$222,A24) -> 147314 | C24: =SUMIFS('Raw Data'!$M$2:$M$222,'Raw Data'!$E$2:$E$222,A24) -> 59003
A25: Home Appliances | B25: =SUMIFS('Raw Data'!$K$2:$K$222,'Raw Data'!$E$2:$E$222,A25) -> 185219 | C25: =SUMIFS('Raw Data'!$M$2:$M$222,'Raw Data'!$E$2:$E$222,A25) -> 70633
A26: Furniture | B26: =SUMIFS('Raw Data'!$K$2:$K$222,'Raw Data'!$E$2:$E$222,A26) -> 269419 | C26: =SUMIFS('Raw Data'!$M$2:$M$222,'Raw Data'!$E$2:$E$222,A26) -> 100709
A27: Apparel | B27: =SUMIFS('Raw Data'!$K$2:$K$222,'Raw Data'!$E$2:$E$222,A27) -> 102413 | C27: =SUMIFS('Raw Data'!$M$2:$M$222,'Raw Data'!$E$2:$E$222,A27) -> 37109
A28: Stationery | B28: =SUMIFS('Raw Data'!$K$2:$K$222,'Raw Data'!$E$2:$E$222,A28) -> 58563 | C28: =SUMIFS('Raw Data'!$M$2:$M$222,'Raw Data'!$E$2:$E$222,A28) -> 20277
A31: Product-wise Revenue (Top-Selling Products)
A32: Product | B32: Revenue (₹) | C32: Units Sold
A33: Office Chair | B33: =SUMIFS('Raw Data'!$K$2:$K$222,'Raw Data'!$F$2:$F$222,A33) -> 111968 | C33: =SUMIFS('Raw Data'!$H$2:$H$222,'Raw Data'!$F$2:$F$222,A33) -> 32
A34: Air Fryer | B34: =SUMIFS('Raw Data'!$K$2:$K$222,'Raw Data'!$F$2:$F$222,A34) -> 94473 | C34: =SUMIFS('Raw Data'!$H$2:$H$222,'Raw Data'!$F$2:$F$222,A34) -> 27
A35: Bookshelf | B35: =SUMIFS('Raw Data'!$K$2:$K$222,'Raw Data'!$F$2:$F$222,A35) -> 83972 | C35: =SUMIFS('Raw Data'!$H$2:$H$222,'Raw Data'!$F$2:$F$222,A35) -> 28
A36: Study Table | B36: =SUMIFS('Raw Data'!$K$2:$K$222,'Raw Data'!$F$2:$F$222,A36) -> 73479 | C36: =SUMIFS('Raw Data'!$H$2:$H$222,'Raw Data'!$F$2:$F$222,A36) -> 21
A37: Power Bank | B37: =SUMIFS('Raw Data'!$K$2:$K$222,'Raw Data'!$F$2:$F$222,A37) -> 73479 | C37: =SUMIFS('Raw Data'!$H$2:$H$222,'Raw Data'!$F$2:$F$222,A37) -> 21
A38: Mixer Grinder | B38: =SUMIFS('Raw Data'!$K$2:$K$222,'Raw Data'!$F$2:$F$222,A38) -> 69972 | C38: =SUMIFS('Raw Data'!$H$2:$H$222,'Raw Data'!$F$2:$F$222,A38) -> 28
A39: Rain Jacket | B39: =SUMIFS('Raw Data'!$K$2:$K$222,'Raw Data'!$F$2:$F$222,A39) -> 65967 | C39: =SUMIFS('Raw Data'!$H$2:$H$222,'Raw Data'!$F$2:$F$222,A39) -> 33
A40: Smart Watch | B40: =SUMIFS('Raw Data'!$K$2:$K$222,'Raw Data'!$F$2:$F$222,A40) -> 34477 | C40: =SUMIFS('Raw Data'!$H$2:$H$222,'Raw Data'!$F$2:$F$222,A40) -> 23
A41: Desk Organizer | B41: =SUMIFS('Raw Data'!$K$2:$K$222,'Raw Data'!$F$2:$F$222,A41) -> 29985 | C41: =SUMIFS('Raw Data'!$H$2:$H$222,'Raw Data'!$F$2:$F$222,A41) -> 15
A42: Bluetooth Speaker | B42: =SUMIFS('Raw Data'!$K$2:$K$222,'Raw Data'!$F$2:$F$222,A42) -> 28971 | C42: =SUMIFS('Raw Data'!$H$2:$H$222,'Raw Data'!$F$2:$F$222,A42) -> 29
A43: Notebook Set | B43: =SUMIFS('Raw Data'!$K$2:$K$222,'Raw Data'!$F$2:$F$222,A43) -> 28578 | C43: =SUMIFS('Raw Data'!$H$2:$H$222,'Raw Data'!$F$2:$F$222,A43) -> 22
A44: Electric Kettle | B44: =SUMIFS('Raw Data'!$K$2:$K$222,'Raw Data'!$F$2:$F$222,A44) -> 20774 | C44: =SUMIFS('Raw Data'!$H$2:$H$222,'Raw Data'!$F$2:$F$222,A44) -> 26
... A47: Wireless Earbuds | B47: =SUMIFS('Raw Data'!$K$2:$K$222,'Raw Data'!$F$2:$F$222,A47) -> 10387 | C47: =SUMIFS('Raw Data'!$H$2:$H$222,'Raw Data'!$F$2:$F$222,A47) -> 13

Sheet Customer Segmentation
A1: Customer Segmentation & Churn Risk (RFM Analysis)
A3: Report Date: | B3: 46186
A5: CustomerID | B5: Last Purchase Date | C5: Recency (days) | D5: Frequency (orders) | E5: Monetary (₹) | F5: RFM Segment | G5: Churn Risk | I5: Churn Risk Distribution
A6: CUST-001 | B6: =_xlfn.MAXIFS('Raw Data'!$B$2:$B$222,'Raw Data'!$G$2:$G$222,A6) -> 46126 | C6: =$B$3-B6 -> 60 | D6: =COUNTIFS('Raw Data'!$G$2:$G$222,A6) -> 2 | E6: =SUMIFS('Raw Data'!$K$2:$K$222,'Raw Data'!$G$2:$G$222,A6) -> 3997 | F6: =IF(AND(C6<=30,D6>=6),"Champion",IF(AND(C6<=45,D6>=4),"Loyal",IF(AND(C6<=60,D6>=2),"Potential Loyalist",IF(C6<=75,"At Risk","Lost")))) -> Potential Loyalist | G6: =IF(C6>60,"High",""&IF(C6>35,"Medium","Low")) -> Medium | I6: Risk Level | J6: Customers
A7: CUST-002 | B7: =_xlfn.MAXIFS('Raw Data'!$B$2:$B$222,'Raw Data'!$G$2:$G$222,A7) -> 46153 | C7: =$B$3-B7 -> 33 | D7: =COUNTIFS('Raw Data'!$G$2:$G$222,A7) -> 1 | E7: =SUMIFS('Raw Data'!$K$2:$K$222,'Raw Data'!$G$2:$G$222,A7) -> 799 | F7: =IF(AND(C7<=30,D7>=6),"Champion",IF(AND(C7<=45,D7>=4),"Loyal",IF(AND(C7<=60,D7>=2),"Potential Loyalist",IF(C7<=75,"At Risk","Lost")))) -> At Risk | G7: =IF(C7>60,"High",""&IF(C7>35,"Medium","Low")) -> Low | I7: High | J7: =COUNTIF(G6:G50,"High") -> 6
A8: CUST-003 | B8: =_xlfn.MAXIFS('Raw Data'!$B$2:$B$222,'Raw Data'!$G$2:$G$222,A8) -> 46167 | C8: =$B$3-B8 -> 19 | D8: =COUNTIFS('Raw Data'!$G$2:$G$222,A8) -> 6 | E8: =SUMIFS('Raw Data'!$K$2:$K$222,'Raw Data'!$G$2:$G$222,A8) -> 22992 | F8: =IF(AND(C8<=30,D8>=6),"Champion",IF(AND(C8<=45,D8>=4),"Loyal",IF(AND(C8<=60,D8>=2),"Potential Loyalist",IF(C8<=75,"At Risk","Lost")))) -> Champion | G8: =IF(C8>60,"High",""&IF(C8>35,"Medium","Low")) -> Low | I8: Medium | J8: =COUNTIF(G6:G50,"Medium") -> 6
A9: CUST-004 | B9: =_xlfn.MAXIFS('Raw Data'!$B$2:$B$222,'Raw Data'!$G$2:$G$222,A9) -> 46176 | C9: =$B$3-B9 -> 10 | D9: =COUNTIFS('Raw Data'!$G$2:$G$222,A9) -> 5 | E9: =SUMIFS('Raw Data'!$K$2:$K$222,'Raw Data'!$G$2:$G$222,A9) -> 12294 | F9: =IF(AND(C9<=30,D9>=6),"Champion",IF(AND(C9<=45,D9>=4),"Loyal",IF(AND(C9<=60,D9>=2),"Potential Loyalist",IF(C9<=75,"At Risk","Lost")))) -> Loyal | G9: =IF(C9>60,"High",""&IF(C9>35,"Medium","Low")) -> Low | I9: Low | J9: =COUNTIF(G6:G50,"Low") -> 33
A10: CUST-005 | B10: =_xlfn.MAXIFS('Raw Data'!$B$2:$B$222,'Raw Data'!$G$2:$G$222,A10) -> 46182 | C10: =$B$3-B10 -> 4 | D10: =COUNTIFS('Raw Data'!$G$2:$G$222,A10) -> 8 | E10: =SUMIFS('Raw Data'!$K$2:$K$222,'Raw Data'!$G$2:$G$222,A10) -> 26387 | F10: =IF(AND(C10<=30,D10>=6),"Champion",IF(AND(C10<=45,D10>=4),"Loyal",IF(AND(C10<=60,D10>=2),"Potential Loyalist",IF(C10<=75,"At Risk","Lost")))) -> Champion | G10: =IF(C10>60,"High",""&IF(C10>35,"Medium","Low")) -> Low
A11: CUST-006 | B11: =_xlfn.MAXIFS('Raw Data'!$B$2:$B$222,'Raw Data'!$G$2:$G$222,A11) -> 46155 | C11: =$B$3-B11 -> 31 | D11: =COUNTIFS('Raw Data'!$G$2:$G$222,A11) -> 3 | E11: =SUMIFS('Raw Data'!$K$2:$K$222,'Raw Data'!$G$2:$G$222,A11) -> 11294 | F11: =IF(AND(C11<=30,D11>=6),"Champion",IF(AND(C11<=45,D11>=4),"Loyal",IF(AND(C11<=60,D11>=2),"Potential Loyalist",IF(C11<=75,"At Risk","Lost")))) -> Potential Loyalist | G11: =IF(C11>60,"High",""&IF(C11>35,"Medium","Low")) -> Low
A12: CUST-007 | B12: =_xlfn.MAXIFS('Raw Data'!$B$2:$B$222,'Raw Data'!$G$2:$G$222,A12) -> 46183 | C12: =$B$3-B12 -> 3 | D12: =COUNTIFS('Raw Data'!$G$2:$G$222,A12) -> 5 | E12: =SUMIFS('Raw Data'!$K$2:$K$222,'Raw Data'!$G$2:$G$222,A12) -> 5793 | F12: =IF(AND(C12<=30,D12>=6),"Champion",IF(AND(C12<=45,D12>=4),"Loyal",IF(AND(C12<=60,D12>=2),"Potential Loyalist",IF(C12<=75,"At Risk","Lost")))) -> Loyal | G12: =IF(C12>60,"High",""&IF(C12>35,"Medium","Low")) -> Low
A13: CUST-008 | B13: =_xlfn.MAXIFS('Raw Data'!$B$2:$B$222,'Raw Data'!$G$2:$G$222,A13) -> 46143 | C13: =$B$3-B13 -> 43 | D13: =COUNTIFS('Raw Data'!$G$2:$G$222,A13) -> 4 | E13: =SUMIFS('Raw Data'!$K$2:$K$222,'Raw Data'!$G$2:$G$222,A13) -> 14793 | F13: =IF(AND(C13<=30,D13>=6),"Champion",IF(AND(C13<=45,D13>=4),"Loyal",IF(AND(C13<=60,D13>=2),"Potential Loyalist",IF(C13<=75,"At Risk","Lost")))) -> Loyal | G13: =IF(C13>60,"High",""&IF(C13>35,"Medium","Low")) -> Medium
A14: CUST-009 | B14: =_xlfn.MAXIFS('Raw Data'!$B$2:$B$222,'Raw Data'!$G$2:$G$222,A14) -> 46121 | C14: =$B$3-B14 -> 65 | D14: =COUNTIFS('Raw Data'!$G$2:$G$222,A14) -> 4 | E14: =SUMIFS('Raw Data'!$K$2:$K$222,'Raw Data'!$G$2:$G$222,A14) -> 7094 | F14: =IF(AND(C14<=30,D14>=6),"Champion",IF(AND(C14<=45,D14>=4),"Loyal",IF(AND(C14<=60,D14>=2),"Potential Loyalist",IF(C14<=75,"At Risk","Lost")))) -> At Risk | G14: =IF(C14>60,"High",""&IF(C14>35,"Medium","Low")) -> High
A15: CUST-010 | B15: =_xlfn.MAXIFS('Raw Data'!$B$2:$B$222,'Raw Data'!$G$2:$G$222,A15) -> 46165 | C15: =$B$3-B15 -> 21 | D15: =COUNTIFS('Raw Data'!$G$2:$G$222,A15) -> 4 | E15: =SUMIFS('Raw Data'!$K$2:$K$222,'Raw Data'!$G$2:$G$222,A15) -> 9495 | F15: =IF(AND(C15<=30,D15>=6),"Champion",IF(AND(C15<=45,D15>=4),"Loyal",IF(AND(C15<=60,D15>=2),"Potential Loyalist",IF(C15<=75,"At Risk","Lost")))) -> Loyal | G15: =IF(C15>60,"High",""&IF(C15>35,"Medium","Low")) -> Low
A16: CUST-011 | B16: =_xlfn.MAXIFS('Raw Data'!$B$2:$B$222,'Raw Data'!$G$2:$G$222,A16) -> 46177 | C16: =$B$3-B16 -> 9 | D16: =COUNTIFS('Raw Data'!$G$2:$G$222,A16) -> 6 | E16: =SUMIFS('Raw Data'!$K$2:$K$222,'Raw Data'!$G$2:$G$222,A16) -> 21590 | F16: =IF(AND(C16<=30,D16>=6),"Champion",IF(AND(C16<=45,D16>=4),"Loyal",IF(AND(C16<=60,D16>=2),"Potential Loyalist",IF(C16<=75,"At Risk","Lost")))) -> Champion | G16: =IF(C16>60,"High",""&IF(C16>35,"Medium","Low")) -> Low
A17: CUST-012 | B17: =_xlfn.MAXIFS('Raw Data'!$B$2:$B$222,'Raw Data'!$G$2:$G$222,A17) -> 46154 | C17: =$B$3-B17 -> 32 | D17: =COUNTIFS('Raw Data'!$G$2:$G$222,A17) -> 2 | E17: =SUMIFS('Raw Data'!$K$2:$K$222,'Raw Data'!$G$2:$G$222,A17) -> 8596 | F17: =IF(AND(C17<=30,D17>=6),"Champion",IF(AND(C17<=45,D17>=4),"Loyal",IF(AND(C17<=60,D17>=2),"Potential Loyalist",IF(C17<=75,"At Risk","Lost")))) -> Potential Loyalist | G17: =IF(C17>60,"High",""&IF(C17>35,"Medium","Low")) -> Low
A18: CUST-013 | B18: =_xlfn.MAXIFS('Raw Data'!$B$2:$B$222,'Raw Data'!$G$2:$G$222,A18) -> 46183 | C18: =$B$3-B18 -> 3 | D18: =COUNTIFS('Raw Data'!$G$2:$G$222,A18) -> 6 | E18: =SUMIFS('Raw Data'!$K$2:$K$222,'Raw Data'!$G$2:$G$222,A18) -> 22090 | F18: =IF(AND(C18<=30,D18>=6),"Champion",IF(AND(C18<=45,D18>=4),"Loyal",IF(AND(C18<=60,D18>=2),"Potential Loyalist",IF(C18<=75,"At Risk","Lost")))) -> Champion | G18: =IF(C18>60,"High",""&IF(C18>35,"Medium","Low")) -> Low
A19: CUST-014 | B19: =_xlfn.MAXIFS('Raw Data'!$B$2:$B$222,'Raw Data'!$G$2:$G$222,A19) -> 46160 | C19: =$B$3-B19 -> 26 | D19: =COUNTIFS('Raw Data'!$G$2:$G$222,A19) -> 6 | E19: =SUMIFS('Raw Data'!$K$2:$K$222,'Raw Data'!$G$2:$G$222,A19) -> 14788 | F19: =IF(AND(C19<=30,D19>=6),"Champion",IF(AND(C19<=45,D19>=4),"Loyal",IF(AND(C19<=60,D19>=2),"Potential Loyalist",IF(C19<=75,"At Risk","Lost")))) -> Champion | G19: =IF(C19>60,"High",""&IF(C19>35,"Medium","Low")) -> Low
A20: CUST-015 | B20: =_xlfn.MAXIFS('Raw Data'!$B$2:$B$222,'Raw Data'!$G$2:$G$222,A20) -> 46162 | C20: =$B$3-B20 -> 24 | D20: =COUNTIFS('Raw Data'!$G$2:$G$222,A20) -> 3 | E20: =SUMIFS('Raw Data'!$K$2:$K$222,'Raw Data'!$G$2:$G$222,A20) -> 7296 | F20: =IF(AND(C20<=30,D20>=6),"Champion",IF(AND(C20<=45,D20>=4),"Loyal",IF(AND(C20<=60,D20>=2),"Potential Loyalist",IF(C20<=75,"At Risk","Lost")))) -> Potential Loyalist | G20: =IF(C20>60,"High",""&IF(C20>35,"Medium","Low")) -> Low
A21: CUST-016 | B21: =_xlfn.MAXIFS('Raw Data'!$B$2:$B$222,'Raw Data'!$G$2:$G$222,A21) -> 46174 | C21: =$B$3-B21 -> 12 | D21: =COUNTIFS('Raw Data'!$G$2:$G$222,A21) -> 8 | E21: =SUMIFS('Raw Data'!$K$2:$K$222,'Raw Data'!$G$2:$G$222,A21) -> 26486 | F21: =IF(AND(C21<=30,D21>=6),"Champion",IF(AND(C21<=45,D21>=4),"Loyal",IF(AND(C21<=60,D21>=2),"Potential Loyalist",IF(C21<=75,"At Risk","Lost")))) -> Champion | G21: =IF(C21>60,"High",""&IF(C21>35,"Medium","Low")) -> Low
... A50: CUST-045 | B50: =_xlfn.MAXIFS('Raw Data'!$B$2:$B$222,'Raw Data'!$G$2:$G$222,A50) -> 46184 | C50: =$B$3-B50 -> 2 | D50: =COUNTIFS('Raw Data'!$G$2:$G$222,A50) -> 5 | E50: =SUMIFS('Raw Data'!$K$2:$K$222,'Raw Data'!$G$2:$G$222,A50) -> 13893 | F50: =IF(AND(C50<=30,D50>=6),"Champion",IF(AND(C50<=45,D50>=4),"Loyal",IF(AND(C50<=60,D50>=2),"Potential Loyalist",IF(C50<=75,"At Risk","Lost")))) -> Loyal | G50: =IF(C50>60,"High",""&IF(C50>35,"Medium","Low")) -> Low
A53: RFM Segmentation Rule (for reference):
A54: • Champion: purchased within 30 days AND 6+ orders
A55: • Loyal: purchased within 45 days AND 4+ orders
A56: • Potential Loyalist: purchased within 60 days AND 2+ orders
A57: • At Risk: last purchase 61-75 days ago
A58: • Lost: no purchase in over 75 days
A59: • Churn Risk — High: Recency > 60 days | Medium: 36-60 days | Low: <=35 days
